ibis_birdbrain/__init__.py
ibis_birdbrain/__main__.py
ibis_birdbrain/app.py
ibis_birdbrain/bot.py
ibis_birdbrain/cli.py
ibis_birdbrain/strings.py
ibis_birdbrain/attachments/__init__.py
ibis_birdbrain/attachments/data.py
ibis_birdbrain/attachments/text.py
ibis_birdbrain/attachments/viz.py
ibis_birdbrain/commands/__init__.py
ibis_birdbrain/commands/ipy.py
ibis_birdbrain/commands/testing.py
ibis_birdbrain/flows/__init__.py
ibis_birdbrain/flows/data.py
ibis_birdbrain/logging/__init__.py
ibis_birdbrain/messages/__init__.py
ibis_birdbrain/messages/email.py
ibis_birdbrain/tasks/__init__.py
ibis_birdbrain/tasks/sql.py
ibis_birdbrain/utils/attachments.py
ibis_birdbrain/utils/messages.py
ibis_birdbrain/utils/strings.py
ibis_birdbrain/utils/web.py
ibis_birdbrain-0.1.0.dist-info/METADATA
ibis_birdbrain-0.1.0.dist-info/WHEEL
ibis_birdbrain-0.1.0.dist-info/entry_points.txt
ibis_birdbrain-0.1.0.dist-info/licenses/LICENSE
ibis_birdbrain-0.1.0.dist-info/RECORD
