Metadata-Version: 2.1
Name: ibis-birdbrain
Version: 0.1.0
Summary: the portable Python LM-powered data bot
Project-URL: Homepage, https://github.com/ibis-project/ibis-birdbrain
Project-URL: Bug Tracker, https://github.com/ibis-project/ibis-birdbrain/issues
Author-email: Cody <cody@dkdc.dev>
License-File: LICENSE
Classifier: License :: OSI Approved :: MIT License
Classifier: Operating System :: OS Independent
Classifier: Programming Language :: Python :: 3
Requires-Python: >=3.11
Requires-Dist: duckduckgo-search
Requires-Dist: html2text
Requires-Dist: httpx
Requires-Dist: ibis-framework[duckdb,examples]
Requires-Dist: ipython
Requires-Dist: marvin<3,>2
Requires-Dist: pillow
Requires-Dist: plotly
Requires-Dist: python-dotenv
Requires-Dist: requests
Requires-Dist: streamlit
Requires-Dist: toml
Requires-Dist: typer[all]
